[
  {
    "Constant": [],
    "submodules": [],
    "Function": [],
    "Variable": [],
    "stripped_doc": [],
    "type": "Module",
    "Deprecated": [],
    "desc": "Make the `shift` key more useful...",
    "Constructor": [],
    "items": [
      {
        "def": "ShiftParentheses:start()",
        "name": "start",
        "doc": "Start sending parentheses when `shift` is pressed and released in isolation",
        "stripped_doc": [
          "Start sending parentheses when `shift` is pressed and released in isolation"
        ],
        "notes": [],
        "signature": "ShiftParentheses:start()",
        "type": "Method",
        "returns": [],
        "desc": "Start sending parentheses when `shift` is pressed and released in isolation",
        "parameters": []
      },
      {
        "def": "ShiftParentheses:stop()",
        "name": "stop",
        "doc": "Stop sending parentheses when `shift` is pressed and released in isolation",
        "stripped_doc": [
          "Stop sending parentheses when `shift` is pressed and released in isolation"
        ],
        "notes": [],
        "signature": "ShiftParentheses:stop()",
        "type": "Method",
        "returns": [],
        "desc": "Stop sending parentheses when `shift` is pressed and released in isolation",
        "parameters": []
      }
    ],
    "Method": [
      {
        "def": "ShiftParentheses:start()",
        "name": "start",
        "doc": "Start sending parentheses when `shift` is pressed and released in isolation",
        "stripped_doc": [
          "Start sending parentheses when `shift` is pressed and released in isolation"
        ],
        "notes": [],
        "signature": "ShiftParentheses:start()",
        "type": "Method",
        "returns": [],
        "desc": "Start sending parentheses when `shift` is pressed and released in isolation",
        "parameters": []
      },
      {
        "def": "ShiftParentheses:stop()",
        "name": "stop",
        "doc": "Stop sending parentheses when `shift` is pressed and released in isolation",
        "stripped_doc": [
          "Stop sending parentheses when `shift` is pressed and released in isolation"
        ],
        "notes": [],
        "signature": "ShiftParentheses:stop()",
        "type": "Method",
        "returns": [],
        "desc": "Stop sending parentheses when `shift` is pressed and released in isolation",
        "parameters": []
      }
    ],
    "Command": [],
    "doc": "Make the `shift` key more useful: If the `shift` key is tapped, send a\npair of parentheses and locate the cursor between them. If the `shift`\nkey is held down and used in combination with another key, then provide\nthe normal `shift` key behavior.",
    "Field": [],
    "name": "ShiftParentheses"
  }
]
